cli/__init__.py
cli/main.py
cli/commands/__init__.py
cli/commands/base.py
cli/commands/project.py
cli/commands/version.py
cli/core/__init__.py
cli/core/config.py
cli/core/exceptions.py
cli/service/__init__.py
cli/service/database_service.py
cli/service/project_service.py
cli/service/requirements_service.py
cli/service/venv_service.py
cli/service/interface/__init__.py
cli/service/interface/base_service.py
cli/templates/__init__.py
cli/templates/__pycache__/__init__.cpython-311.pyc
cli/templates/config/__init__.py
cli/templates/config/settings_template.py
cli/templates/config/__pycache__/__init__.cpython-311.pyc
cli/templates/config/__pycache__/settings_template.cpython-311.pyc
cli/templates/project/__init__.py
cli/templates/project/database_template.py
cli/templates/project/main_template.py
cli/templates/project/project_structure.py
cli/templates/project/__pycache__/__init__.cpython-311.pyc
cli/templates/project/__pycache__/database_template.cpython-311.pyc
cli/templates/project/__pycache__/main_template.cpython-311.pyc
cli/templates/project/__pycache__/project_structure.cpython-311.pyc
cli/utils/__init__.py
cli/utils/banner.py
cli/utils/database_type.py
cli/utils/terminal.py
cli/utils/validator.py
fastapi_starter_cli-0.1.0.dev0.dist-info/LICENSE
fastapi_starter_cli-0.1.0.dev0.dist-info/METADATA
fastapi_starter_cli-0.1.0.dev0.dist-info/WHEEL
fastapi_starter_cli-0.1.0.dev0.dist-info/entry_points.txt
fastapi_starter_cli-0.1.0.dev0.dist-info/top_level.txt
fastapi_starter_cli-0.1.0.dev0.dist-info/RECORD
