Metadata-Version: 2.1
Name: fastapi-starter-cli
Version: 0.1.0.dev0
Summary: CLI tool for generating FastAPI projects
Home-page: https://github.com/RobertoRuben/fastapi-starter-cli
Author: betooo
Classifier: Programming Language :: Python :: 3.8
Classifier: License :: OSI Approved :: MIT License
Classifier: Operating System :: OS Independent
Requires-Python: >=3.8
License-File: LICENSE
Requires-Dist: typer>=0.15.0
Requires-Dist: colorama>=0.4.6
Requires-Dist: rich>=13.9.0
